gitbud/__init__.py
gitbud/gitbud.py
gitbud-0.0.7.dist-info/licenses/LICENSE
gitbud-0.0.7.dist-info/METADATA
gitbud-0.0.7.dist-info/WHEEL
gitbud-0.0.7.dist-info/top_level.txt
gitbud-0.0.7.dist-info/RECORD
