Metadata-Version: 2.4
Name: gitbud
Version: 0.0.7
License-File: LICENSE
Requires-Dist: GitPython
Dynamic: description
Dynamic: license-file
Dynamic: requires-dist
